[
  {
    "titolo": "Vasco Rossi Live",
    "data": "2025-10-15",
    "luogo": "Stadio Olimpico, Roma",
    "link": "https://www.ticketone.it/event/vasco-rossi-roma",
    "immagine": "https://vivafest.github.io/ticket-affiliate/images/vasco.jpg"
  },
  {
    "titolo": "Eros Ramazzotti Tour",
    "data": "2025-10-20",
    "luogo": "Mediolanum Forum, Milano",
    "link": "https://www.ticketone.it/event/eros-ramazzotti-milano",
    "immagine": "https://vivafest.github.io/ticket-affiliate/images/eros.jpg"
  }
]
